athena/__init__.py
athena/active.py
athena/feature_map.py
athena/kas.py
athena/local.py
athena/local_classification.py
athena/meta.py
athena/nll.py
athena/projection_factory.py
athena/subspaces.py
athena/utils.py
athena_mathlab-0.1.2.post2304.dist-info/LICENSE.rst
athena_mathlab-0.1.2.post2304.dist-info/METADATA
athena_mathlab-0.1.2.post2304.dist-info/WHEEL
athena_mathlab-0.1.2.post2304.dist-info/top_level.txt
athena_mathlab-0.1.2.post2304.dist-info/RECORD
