Metadata-Version: 2.1
Name: athena-mathlab
Version: 0.1.2.post2304
Summary: Advanced Techniques for High dimensional parameter spaces to Enhance Numerical Analysis
Home-page: https://github.com/mathLab/ATHENA
Author: Marco Tezzele, Francesco Romor
Author-email: marcotez@gmail.com, francesco.romor@gmail.com
License: MIT
Keywords: parameter-space-reduction active-subspaces kernel-active-subspaces model-reduction sensitivity-analysis nonlinear-level-set-learning
Classifier: Development Status :: 5 - Production/Stable
Classifier: License :: OSI Approved :: MIT License
Classifier: Programming Language :: Python :: 3.8
Classifier: Intended Audience :: Science/Research
Classifier: Topic :: Scientific/Engineering :: Mathematics
License-File: LICENSE.rst
Requires-Dist: numpy
Requires-Dist: scipy
Requires-Dist: matplotlib
Requires-Dist: torch
Requires-Dist: GPyOpt
Requires-Dist: scikit-learn
Requires-Dist: scikit-learn-extra
Provides-Extra: docs
Requires-Dist: Sphinx (>=1.4) ; extra == 'docs'
Requires-Dist: sphinx-rtd-theme ; extra == 'docs'
Provides-Extra: formatting
Requires-Dist: yapf ; extra == 'formatting'
Provides-Extra: test
Requires-Dist: pytest ; extra == 'test'
Requires-Dist: pytest-cov ; extra == 'test'
Provides-Extra: tutorials
Requires-Dist: pyro ; extra == 'tutorials'
Requires-Dist: pyhmc ; extra == 'tutorials'
